LICENSE
MANIFEST.in
README.md
setup.py
almo_cli/__init__.py
almo_cli/almo_cli.py
almo_cli/preview.py
almo_cli/runner.py
almo_cli/utils.py
almo_cli/version.yaml
almo_cli.egg-info/PKG-INFO
almo_cli.egg-info/SOURCES.txt
almo_cli.egg-info/dependency_links.txt
almo_cli.egg-info/entry_points.txt
almo_cli.egg-info/requires.txt
almo_cli.egg-info/top_level.txt