Metadata-Version: 2.1
Name: almo-cli
Version: 0.0.3
License-File: LICENSE
Requires-Dist: PyYAML
Requires-Dist: argparse
Requires-Dist: almo==v0.9.4-alpha
Requires-Dist: livereload
Requires-Dist: jinja2
